Metadata-Version: 2.1
Name: secretvalidator
Version: 0.1.12
License-File: LICENSE
Requires-Dist: click
Requires-Dist: requests
Requires-Dist: setuptools
Requires-Dist: twine
